tts_uk/alignment.py
tts_uk/attribute_prediction_model.py
tts_uk/audio_processing.py
tts_uk/autoregressive_flow.py
tts_uk/common.py
tts_uk/config.py
tts_uk/data.py
tts_uk/inference.py
tts_uk/partialconv1d.py
tts_uk/radtts.py
tts_uk/splines.py
tts_uk/torch_env.py
tts_uk/transformer.py
vocos/__init__.py
vocos/feature_extractors.py
vocos/heads.py
vocos/models.py
vocos/modules.py
vocos/pretrained.py
vocos/spectral_ops.py
tts_uk-1.3.7.dist-info/METADATA
tts_uk-1.3.7.dist-info/WHEEL
tts_uk-1.3.7.dist-info/RECORD
