Metadata-Version: 2.4
Name: tts_uk
Version: 1.3.7
Summary: High-fidelity speech synthesis for Ukrainian using modern neural networks.
Project-URL: Homepage, https://github.com/egorsmkv/tts_uk
Project-URL: Repository, https://github.com/egorsmkv/tts_uk
Author-email: Yehor Smoliakov <egorsmkv@gmail.com>
License-Expression: MIT
Keywords: audio,media,sound,synthesis,text-to-speech,tts,ukrainian,wav,wave
Classifier: Development Status :: 5 - Production/Stable
Classifier: Intended Audience :: Developers
Classifier: Intended Audience :: Information Technology
Classifier: Intended Audience :: Science/Research
Classifier: License :: OSI Approved :: MIT License
Classifier: Operating System :: OS Independent
Classifier: Programming Language :: Python :: 3
Classifier: Programming Language :: Python :: 3 :: Only
Classifier: Topic :: Scientific/Engineering
Classifier: Topic :: Scientific/Engineering :: Artificial Intelligence
Classifier: Topic :: Software Development
Classifier: Topic :: Software Development :: Libraries :: Python Modules
Requires-Python: >=3.9
Requires-Dist: huggingface-hub>=0.29
Requires-Dist: jinja2>=3.1.6
Requires-Dist: librosa>=0.10
Requires-Dist: numba>=0.60
Requires-Dist: scipy>=1.13
Requires-Dist: torch>=2.6
Requires-Dist: torchaudio>=2.6
Provides-Extra: dev
Requires-Dist: ruff>=0.9; extra == 'dev'
